okonomiyaki/__init__.py
okonomiyaki/__main__.py
okonomiyaki/_version.py
okonomiyaki/errors.py
okonomiyaki/_cli/__init__.py
okonomiyaki/_cli/tests/__init__.py
okonomiyaki/_cli/tests/test_cli.py
okonomiyaki/file_formats/__init__.py
okonomiyaki/file_formats/_egg_info.py
okonomiyaki/file_formats/_package_info.py
okonomiyaki/file_formats/_wheel_common.py
okonomiyaki/file_formats/_wheel_info.py
okonomiyaki/file_formats/egg.py
okonomiyaki/file_formats/legacy.py
okonomiyaki/file_formats/setuptools_egg.py
okonomiyaki/file_formats/_blacklist/__init__.py
okonomiyaki/file_formats/_blacklist/pkg_info_data.py
okonomiyaki/file_formats/_blacklist/platform_tag.py
okonomiyaki/file_formats/_blacklist/python_tag.py
okonomiyaki/file_formats/tests/__init__.py
okonomiyaki/file_formats/tests/common.py
okonomiyaki/file_formats/tests/test__egg_info.py
okonomiyaki/file_formats/tests/test__package_info.py
okonomiyaki/file_formats/tests/test__wheel_info.py
okonomiyaki/file_formats/tests/test_egg_file_format.py
okonomiyaki/file_formats/tests/test_legacy.py
okonomiyaki/file_formats/tests/test_setuptools_file_format.py
okonomiyaki/platforms/__init__.py
okonomiyaki/platforms/_arch.py
okonomiyaki/platforms/_pep425_impl.py
okonomiyaki/platforms/_platform.py
okonomiyaki/platforms/abi.py
okonomiyaki/platforms/epd_platform.py
okonomiyaki/platforms/pep425.py
okonomiyaki/platforms/platform_filters.py
okonomiyaki/platforms/python_implementation.py
okonomiyaki/platforms/tests/__init__.py
okonomiyaki/platforms/tests/common.py
okonomiyaki/platforms/tests/test__arch.py
okonomiyaki/platforms/tests/test_abi.py
okonomiyaki/platforms/tests/test_epd_platform.py
okonomiyaki/platforms/tests/test_pep425.py
okonomiyaki/platforms/tests/test_platform.py
okonomiyaki/platforms/tests/test_platform_filters.py
okonomiyaki/platforms/tests/test_python_implementation.py
okonomiyaki/runtimes/__init__.py
okonomiyaki/runtimes/common.py
okonomiyaki/runtimes/runtime.py
okonomiyaki/runtimes/runtime_info.py
okonomiyaki-2.0.0.dist-info/LICENSE.txt
okonomiyaki-2.0.0.dist-info/METADATA
okonomiyaki-2.0.0.dist-info/WHEEL
okonomiyaki-2.0.0.dist-info/top_level.txt
okonomiyaki-2.0.0.dist-info/RECORD
