Metadata-Version: 2.1
Name: okonomiyaki
Version: 2.0.0
Summary: Self-contained library to deal with metadata in Enthought-specific egg and runtime archives
Home-page: https://github.com/enthought/okonomiyaki
Author: Enthought Inc.
Author-email: info@enthough.com
License: BSD-3-Clause
Classifier: Programming Language :: Python :: 3
Classifier: Programming Language :: Python :: 3.6
Classifier: Programming Language :: Python :: 3.7
Classifier: Programming Language :: Python :: 3.8
Classifier: Programming Language :: Python :: 3.9
Classifier: Programming Language :: Python :: 3.10
Classifier: Programming Language :: Python :: 3.11
Classifier: Programming Language :: Python :: 3.12
Requires-Python: >=3.6
Provides-Extra: test
Provides-Extra: platforms
Provides-Extra: formats
Provides-Extra: all
